README.md
setup.cfg
setup.py
andreas_distributions.egg-info/PKG-INFO
andreas_distributions.egg-info/SOURCES.txt
andreas_distributions.egg-info/dependency_links.txt
andreas_distributions.egg-info/not-zip-safe
andreas_distributions.egg-info/top_level.txt
distributions/Binomialdistribution.py
distributions/Gaussiandistribution.py
distributions/Generaldistribution.py
distributions/__init__.py